{
    "openapi": "3.0.0",
    "info": {
        "title": "Laravel API",
        "description": "API documentation",
        "version": "1.0.0"
    },
    "paths": {
        "/api/register": {
            "post": {
                "tags": [
                    "Auth"
                ],
                "summary": "Register",
                "operationId": "8a56853624e025573120a09a4c75d468",
                "requestBody": {
                    "content": {
                        "application/json": {
                            "schema": {
                                "properties": {
                                    "": {
                                        "properties": {
                                            "name": {
                                                "type": "string"
                                            },
                                            "email": {
                                                "type": "string"
                                            },
                                            "password": {
                                                "type": "string"
                                            }
                                        },
                                        "type": "object"
                                    }
                                },
                                "type": "object",
                                "example": {
                                    "name": "John",
                                    "email": "john@test.com",
                                    "password": "johnjohn1"
                                }
                            }
                        }
                    }
                },
                "responses": {
                    "200": {
                        "description": "Success",
                        "content": {
                            "application/json": {
                                "schema": {
                                    "properties": {
                                        "meta": {
                                            "properties": {
                                                "code": {
                                                    "type": "number",
                                                    "example": 200
                                                },
                                                "status": {
                                                    "type": "string",
                                                    "example": "success"
                                                },
                                                "message": {
                                                    "type": "string",
                                                    "example": null
                                                }
                                            },
                                            "type": "object"
                                        }
                                    },
                                    "type": "object"
                                }
                            }
                        }
                    }
                }
            }
        }
    },
    "tags": [
        {
            "name": "Auth",
            "description": "Auth"
        }
    ]
}